{
    "ffmc": 90.50870361328126,
    "isi": 6.643186092376708,
    "bui": 62.74895477294922,
    "years": [
        2010,
        2011,
        2012,
        2013,
        2014,
        2015,
        2016,
        2017,
        2018,
        2019
    ],
    "station": {
        "code": "113",
        "name": "BOB QUINN LAKE",
        "lat": "56.9809830",
        "long": "-130.2508000",
        "ecodivision_name": "HUMID CONTINENTAL HIGHLANDS",
        "core_season": {
            "start_month": "5",
            "start_day": "15",
            "end_month": "8",
            "end_day": "31"
        }
    }
}